{
  "title": "同程金融App礼品卡套路",
  "exposureTime": "2024-03-15",
  "industry": "互联网金融",
  "desc": "2024年央视“3·15”晚会曝光了同程金融App礼品卡套路，揭露了该平台通过售卖礼品卡变相发放高息贷款，并以‘礼品卡+权益’的形式掩盖真实利率，诱导用户陷入高额债务陷阱。这些行为不仅损害了消费者权益，还暴露了互联网金融平台的监管漏洞。",
  "url": "",
  "companyList": [
    {
      "name": "同程数科（上海）科技有限公司",
      "legalPerson": "马和平"
    }
  ],
  "brandList": [
    {
      "name": "同程金融App"
    }
  ],
  "productType": 2,
  "productList": [
    {
      "name": "礼品卡变相贷款",
      "issueType": "用户购买礼品卡后需兑换成现金，实际为变相发放高息贷款。",
      "remark": "礼品卡面值1000元，用户仅能兑换700元现金，剩余300元用于购买‘权益’。"
    },
    {
      "name": "高息贷款",
      "issueType": "通过‘礼品卡+权益’形式掩盖真实利率，实际年化利率高达300%以上。",
      "remark": "用户借款1000元，实际到账700元，7天后需还款1000元，利息高达300元。"
    },
    {
      "name": "诱导消费",
      "issueType": "平台通过弹窗广告、短信推送等方式诱导用户购买礼品卡。",
      "remark": "部分用户因急需资金，未仔细阅读条款便购买礼品卡，陷入债务陷阱。"
    },
    {
      "name": "退款难",
      "issueType": "用户申请退款时遭遇拖延或拒绝，平台以‘权益已使用’为由拒绝退款。",
      "remark": "部分用户购买礼品卡后未兑换现金，但仍无法退款。"
    }
  ],
  "penalty": {
    "type": "整改、罚款",
    "amount": "未公开",
    "desc": "同程金融App被要求整改，相关功能暂停运营；市场监管部门介入调查。",
    "response": "同程数科发布声明，承诺整改并优化产品设计，停止礼品卡相关业务。"
  },
  "followUp": {
    "regulatory": "市场监管部门对同程数科展开调查，重点核查礼品卡业务合规性。",
    "brandRes": "同程金融App下架礼品卡相关功能，优化用户退款流程，承诺加强内部管理。"
  }
}