{
  "title": "废旧轮胎翻新乱象",
  "exposureTime": "2022-03-15",
  "industry": "汽车零部件",
  "desc": "2022年央视'3·15'晚会曝光了废旧轮胎翻新行业的严重问题，揭露了部分企业将报废轮胎简单处理后重新上市销售，这些翻新轮胎存在重大安全隐患，极易引发爆胎事故。",
  "url": "",
  "companyList": [
    {
      "name": "河北衡水某轮胎翻新厂",
      "legalPerson": "未公开"
    },
    {
      "name": "山东东营某轮胎加工点",
      "legalPerson": "未公开"
    }
  ],
  "brandList": [
    {
      "name": "翻新轮胎"
    }
  ],
  "productType": 2,
  "productList": [
    {
      "name": "使用报废胎体",
      "issueType": "将已超过使用年限的轮胎进行翻新",
      "remark": "胎体结构已严重老化，强度不足"
    },
    {
      "name": "工艺不达标",
      "issueType": "仅简单打磨胎面后粘贴新胶皮",
      "remark": "未按标准进行硫化处理"
    },
    {
      "name": "虚假标识",
      "issueType": "伪造生产日期和DOT认证标志",
      "remark": "将翻新胎标注为新胎"
    },
    {
      "name": "安全隐患",
      "issueType": "高速行驶时极易发生脱胶、爆胎",
      "remark": "测试显示部分产品在80km/h即出现开裂"
    }
  ],
  "penalty": {
    "type": "查封、刑事立案",
    "amount": "未公开",
    "desc": "涉事窝点被查封，相关责任人被控制",
    "response": "部分加工点辩称'只是修补不是翻新'"
  },
  "followUp": {
    "regulatory": "市场监管总局开展轮胎产品专项整治",
    "brandRes": "正规企业建立废旧轮胎回收溯源系统"
  }
}